brij/__init__.py
brij/utils/__init__.py
brij/utils/msg.py
brij/utils/cli/__init__.py
brij/utils/client/__init__.py
brij/utils/client/base.py
brij/utils/server/__init__.py
brij/utils/server/base.py
brij-0.1.1.dist-info/METADATA
brij-0.1.1.dist-info/WHEEL
brij-0.1.1.dist-info/entry_points.txt
brij-0.1.1.dist-info/RECORD
