Metadata-Version: 2.4
Name: brij
Version: 0.1.1
Summary: Add your description here
Author-email: Sattwik Kumar Sahu <sattwik21@iiserb.ac.in>
Requires-Python: >=3.10
Requires-Dist: blosc>=1.11.3
Requires-Dist: msgpack-numpy>=0.4.8
Requires-Dist: msgpack>=1.1.1
Requires-Dist: numpy>=2.2.6
Requires-Dist: pyzmq>=27.0.1
Requires-Dist: rich>=14.1.0
Requires-Dist: typer>=0.16.0
